hacs/__init__.py
hacs/admin.py
hacs/apps.py
hacs/defaults.py
hacs/django_utils_version.py
hacs/fields.py
hacs/globals.py
hacs/lru_wrapped.py
hacs/middleware.py
hacs/models.py
hacs/urls.py
hacs/utils.py
hacs/generated/.gitignore
hacs/locales/.gitkeep
hacs/management/__init__.py
hacs/management/commands/__init__.py
hacs/management/commands/export_routes.py
hacs/management/commands/import_routes.py
hacs/migrations/0001_initial.py
hacs/migrations/__init__.py
hacs/tests/__init__.py
hacs/tests/test_management_export_routes.py
hacs/tests/test_management_import_routes.py
hacs/tests/test_middleware.py
hacs/tests/test_utils.py
hacs/tests/fixtures/testing_fixture.json
hacs/tests/fixtures/testing_routing_fixture.json
hacs/views/__init__.py
hacs/views/errors.py
hacs-1.0a1.dist-info/DESCRIPTION.rst
hacs-1.0a1.dist-info/METADATA
hacs-1.0a1.dist-info/RECORD
hacs-1.0a1.dist-info/WHEEL
hacs-1.0a1.dist-info/metadata.json
hacs-1.0a1.dist-info/top_level.txt
